PyVirtuinTestComm-0.9.8.dist-info/DESCRIPTION.rst
PyVirtuinTestComm-0.9.8.dist-info/METADATA
PyVirtuinTestComm-0.9.8.dist-info/RECORD
PyVirtuinTestComm-0.9.8.dist-info/WHEEL
PyVirtuinTestComm-0.9.8.dist-info/metadata.json
PyVirtuinTestComm-0.9.8.dist-info/top_level.txt
PyVirtuinTestComm-0.9.8.dist-info/zip-safe
pyvirtuintestcomm/__init__.py
pyvirtuintestcomm/shared.py
pyvirtuintestcomm/virtuintestdispatcher.py
pyvirtuintestcomm/virtuintesthandler.py
pyvirtuintestcomm/virtuintestpublisher.py
pyvirtuintestcomm/virtuintestsubscriber.py
pyvirtuintestcomm/virtuintestviewclient.py
pyvirtuintestcomm/virtuintestviewserver.py
